ALU_8bit/alu_8bit.v
module alu_8bit (
    input [7:0] A, B,
    input [3:0] sel,
    output reg [7:0] out,
    output reg carry
);

always @(A or B or sel) begin
    carry = 0;
    out = 0;
    case (sel)
        4'b0000: {carry, out} = A + B; // Addition
        4'b0001: {carry, out} = A - B; // Subtraction
        4'b0010: out = A & B; // AND
        4'b0011: out = A | B; // OR
        4'b0100: out = A ^ B; // XOR
        4'b0101: out = ~A; // NOT
        4'b0110: out = A << 1; // Logical Shift Left
        4'b0111: out = A >> 1; // Logical Shift Right
        4'b1000: out = A >>> 1; // Arithmetic Shift Right
        4'b1001: out = A; // Pass A
        4'b1010: out = B; // Pass B
        default: out = 8'b0000_0000; // Default case 
    endcase

end
endmodule

ALU_8bit/alu_tb.v
module alu_tb;

    reg [7:0] a,b;
    wire [7:0] out;
    reg [3:0] sel;
    wire carry;

    alu_8bit inst1(
    .A(a),
    .B(b),
    .sel(sel),
    .out(out),
    .carry(carry)
);

    initial 
        begin
            a = 8'd10; b = 8'd5; sel = 4'b0000; #10;
            a = 8'd10; b = 8'd5; sel = 4'b0001; #10;
            a = 8'd10; b = 8'd5; sel = 4'b0010; #10;
            a = 8'd10; b = 8'd5; sel = 4'b0011; #10;
            a = 8'd10; b = 8'd5; sel = 4'b0100; #10;
            a = 8'd10; b = 8'd5; sel = 4'b0101; #10;
            a = 8'd10; b = 8'd5; sel = 4'b0110; #10;
            a = 8'd10; b = 8'd5; sel = 4'b0111; #10;
        $finish;

        end
    initial begin
    $dumpfile("alu.vcd");
    $dumpvars(0, alu_tb);
end

endmodule

ALU_8bit/alu.vcd
$date
	Sat Mar 14 16:27:27 2026
$end
$version
	Icarus Verilog
$end
$timescale
	1s
$end
$scope module alu_tb $end
$var wire 8 ! out [7:0] $end
$var wire 1 " carry $end
$var reg 8 # a [7:0] $end
$var reg 8 $ b [7:0] $end
$var reg 4 % sel [3:0] $end
$scope module inst1 $end
$var wire 8 & A [7:0] $end
$var wire 8 ' B [7:0] $end
$var wire 4 ( sel [3:0] $end
$var reg 1 " carry $end
$var reg 8 ) out [7:0] $end
$upscope $end
$upscope $end
$enddefinitions $end
$comment Show the parameter values. $end
$dumpall
$end
#0
$dumpvars
b1111 )
b0 (
b101 '
b1010 &
b0 %
b101 $
b1010 #
0"
b1111 !
$end
#10
b101 !
b101 )
b1 %
b1 (
#20
b0 !
b0 )
b10 %
b10 (
#30
b1111 !
b1111 )
b11 %
b11 (
#40
b1111 !
b1111 )
b100 %
b100 (
#50
b11110101 !
b11110101 )
b101 %
b101 (
#60
b10100 !
b10100 )
b110 %
b110 (
#70
b101 !
b101 )
b111 %
b111 (
