adder/ripadd.v
module ripadd(
    input wire [3:0] a, b,
    input wire cin,
    output [4:0] sum
);

wire w1, w2, w3;

add1 layer1(a[0], b[0], cin, sum[0], w1);
add1 layer2(a[1], b[1], w1, sum[1], w2);
add1 layer3(a[2], b[2], w2, sum[2], w3);
add1 layer4(a[3], b[3], w3, sum[3], sum[4]);

endmodule


module add1(
    input a, b, cin,
    output sum, carry
);

assign sum   = a ^ b ^ cin;
assign carry = (a & b) | (b & cin) | (a & cin);

endmodule

adder/ripadd_tb.v
module ripadd_tb;

reg [3:0] a, b;
reg cin;
wire [4:0] sum;

ripadd ins1(.a(a), .b(b), .cin(cin), .sum(sum));

initial begin
    a=0;  b=0;  cin=0; #10;
    a=1;  b=1;  cin=0; #10;
    a=7;  b=8;  cin=0; #10;
    a=3;  b=5;  cin=1; #10;
    a=10; b=9;  cin=0; #10;
    a=10; b=9;  cin=1; #10;
    a=15; b=15; cin=0; #10;
    a=15; b=15; cin=1; #10;

    $finish;
end

initial begin
    $monitor("t=%0t | a=%b b=%b cin=%b | sum=%b", $time, a, b, cin, sum);
end

initial begin
    $dumpfile("wave.vcd");
    $dumpvars(0, ripadd_tb);
end

endmodule

adder/wave.vcd
$date
	Wed Apr 15 15:05:02 2026
$end
$version
	Icarus Verilog
$end
$timescale
	1s
$end
$scope module ripadd_tb $end
$var wire 5 ! sum [4:0] $end
$var reg 4 " a [3:0] $end
$var reg 4 # b [3:0] $end
$var reg 1 $ cin $end
$scope module ins1 $end
$var wire 4 % a [3:0] $end
$var wire 4 & b [3:0] $end
$var wire 1 $ cin $end
$var wire 1 ' w3 $end
$var wire 1 ( w2 $end
$var wire 1 ) w1 $end
$var wire 5 * sum [4:0] $end
$scope module layer1 $end
$var wire 1 + a $end
$var wire 1 , b $end
$var wire 1 ) carry $end
$var wire 1 $ cin $end
$var wire 1 - sum $end
$upscope $end
$scope module layer2 $end
$var wire 1 . a $end
$var wire 1 / b $end
$var wire 1 ( carry $end
$var wire 1 ) cin $end
$var wire 1 0 sum $end
$upscope $end
$scope module layer3 $end
$var wire 1 1 a $end
$var wire 1 2 b $end
$var wire 1 ' carry $end
$var wire 1 ( cin $end
$var wire 1 3 sum $end
$upscope $end
$scope module layer4 $end
$var wire 1 4 a $end
$var wire 1 5 b $end
$var wire 1 6 carry $end
$var wire 1 ' cin $end
$var wire 1 7 sum $end
$upscope $end
$upscope $end
$upscope $end
$enddefinitions $end
#0
$dumpvars
07
06
05
04
03
02
01
00
0/
0.
0-
0,
0+
b0 *
0)
0(
0'
b0 &
b0 %
0$
b0 #
b0 "
b0 !
$end
#10
b10 !
b10 *
10
1)
1,
1+
b1 #
b1 &
b1 "
b1 %
#20
06
0'
0)
1-
17
10
0(
b1111 !
b1111 *
13
0,
15
1.
11
b1000 #
b1000 &
b111 "
b111 %
#30
1'
03
1(
00
17
1)
b1001 !
b1001 *
1-
1,
12
05
01
1$
b101 #
b101 &
b11 "
b11 %
#40
0(
07
10
0'
0)
03
16
b10011 !
b10011 *
1-
02
15
0+
14
0$
b1001 #
b1001 &
b1010 "
b1010 %
#50
13
1(
00
1)
b10100 !
b10100 *
0-
1$
#60
17
10
1'
b11110 !
b11110 *
0-
1/
12
1+
11
0$
b1111 #
b1111 &
b1111 "
b1111 %
#70
b11111 !
b11111 *
1-
1$
